exendlr/__init__.py
exendlr/__main__.py
exendlr/reader.py
exendlr-1.0.dist-info/LICENSE
exendlr-1.0.dist-info/WHEEL
exendlr-1.0.dist-info/METADATA
exendlr-1.0.dist-info/RECORD
