Metadata-Version: 2.1
Name: exendlr
Version: 1.0
Summary: Module for reading docker logs
Home-page: https://github.com/Exenifix/ExenDLR
License: MIT
Author: Exenifix
Requires-Python: >=3.7
Classifier: License :: OSI Approved :: MIT License
Classifier: Programming Language :: Python :: 3
Classifier: Programming Language :: Python :: 3.10
Classifier: Programming Language :: Python :: 3.7
Classifier: Programming Language :: Python :: 3.8
Classifier: Programming Language :: Python :: 3.9
Project-URL: Repository, https://github.com/Exenifix/ExenDLR
